pyfldigi/__init__.py
pyfldigi/appmonitor.py
pyfldigi/xmlconfig.py
pyfldigi/client/__init__.py
pyfldigi/client/client.py
pyfldigi/client/flmsg.py
pyfldigi/client/ioconfig.py
pyfldigi/client/log.py
pyfldigi/client/main.py
pyfldigi/client/modem.py
pyfldigi/client/pskreporter.py
pyfldigi/client/rig.py
pyfldigi/client/text.py
pyfldigi/client/transport.py
pyfldigi/client/txmonitor.py
pyfldigi-0.4.dist-info/DESCRIPTION.rst
pyfldigi-0.4.dist-info/METADATA
pyfldigi-0.4.dist-info/RECORD
pyfldigi-0.4.dist-info/WHEEL
pyfldigi-0.4.dist-info/metadata.json
pyfldigi-0.4.dist-info/top_level.txt
tests/test_client.py
