Metadata-Version: 2.0
Name: pyfldigi
Version: 0.4
Summary: Python library to control FLDIGI via XML-RPC
Home-page: https://github.com/KM4YRI/pyFldigi
Author: KM4YRI
Author-email: km4yri@gmail.com
License: License :: OSI Approved :: GNU General Public License v3 (GPLv3)
Keywords: fldigi ham radio hf digital cw morse rtty olivia psk ssb sdr
Platform: UNKNOWN
Classifier: Development Status :: 3 - Alpha
Classifier: Environment :: Console
Classifier: Intended Audience :: Developers
Classifier: Intended Audience :: Science/Research
Classifier: Intended Audience :: Telecommunications Industry
Classifier: Topic :: Software Development :: Build Tools
Classifier: License :: OSI Approved :: GNU General Public License v3 (GPLv3)
Classifier: Natural Language :: English
Classifier: Operating System :: POSIX :: Linux
Classifier: Operating System :: Microsoft :: Windows
Classifier: Operating System :: MacOS :: MacOS X
Classifier: Programming Language :: Python :: 3
Classifier: Programming Language :: Python :: 3.2
Classifier: Programming Language :: Python :: 3.3
Classifier: Programming Language :: Python :: 3.4
Classifier: Programming Language :: Python :: 3.5
Classifier: Programming Language :: Python :: 3.6
Classifier: Topic :: Communications :: Ham Radio
Requires-Dist: requests
